{
    "sources": [
        {
            "id": "free",
            "name": "Free",
            "description": "",
            "category": "utility",
            "parameters": [
                {
                    "name": "login",
                    "rules": [
                        "required"
                    ]z
                },
                {
                    "name": "password",
                    "rules": [
                        "required",
                        "secret"
                    ]
                }
            ]
        }
    ],
    "targets": [

    ]
}